roxyai_api/__init__.py
roxyai_api/com_base.py
roxyai_api/com_definition.py
roxyai_api/com_echo.py
roxyai_api/com_get_image.py
roxyai_api/com_get_probabilities.py
roxyai_api/com_initialize.py
roxyai_api/com_inspect.py
roxyai_api/com_terminate.py
roxyai_api/connection.py
roxyai_api/inspect_buffer.py
roxyai_api/inspect_image.py
roxyai_api/label_info.py
roxyai_api/load_config.py
roxyai_api/svr_base_handler.py
roxyai_api/svr_command_handler.py
roxyai_api-1.13.6.dist-info/METADATA
roxyai_api-1.13.6.dist-info/WHEEL
roxyai_api-1.13.6.dist-info/top_level.txt
roxyai_api-1.13.6.dist-info/RECORD
