Metadata-Version: 2.1
Name: roxyai-api
Version: 1.13.6
Summary: Roxy AI inspect-server python API package
Home-page: https://gitlab.com/roxy-ai/roxy-ai-dev/-/tree/master/python/roxyai-api
Author: Roxy Corp.
Author-email: support@roxy-ai.jp
License: UNKNOWN
Platform: UNKNOWN
Classifier: Programming Language :: Python :: 3.7
Classifier: License :: OSI Approved :: Apache Software License
Classifier: Operating System :: OS Independent
Requires-Dist: numpy (==1.19.3)
Requires-Dist: opencv-python (==4.2.0.34)
Requires-Dist: psutil (==5.8.0)
Requires-Dist: json5 (==0.9.5)
Requires-Dist: termcolor (==1.1.0)
Provides-Extra: develop
Requires-Dist: pytest (==7.0.1) ; extra == 'develop'
Requires-Dist: wheel (==0.37.1) ; extra == 'develop'
Requires-Dist: twine (==3.8.0) ; extra == 'develop'
Requires-Dist: flake8 (==4.0.1) ; extra == 'develop'
